BinaryFileModifier/__init__.py
BinaryFileModifier/linuxBinaryFileModifier.py
BinaryFileModifier/winBinaryFileModifier.py
BinaryFileModifier-1.0.0.dist-info/METADATA
BinaryFileModifier-1.0.0.dist-info/WHEEL
BinaryFileModifier-1.0.0.dist-info/top_level.txt
BinaryFileModifier-1.0.0.dist-info/RECORD
