Metadata-Version: 2.1
Name: BinaryFileModifier
Version: 1.0.0
Summary: The package changes the JavaScript signature in WebDrivers ChromeDriver
Author: Rainer Schmitz
Author-email: rainer.ch.franz87@gmail.com
Classifier: Programming Language :: Python :: 3
Classifier: License :: OSI Approved :: MIT License
Classifier: Operating System :: OS Independent
Requires-Python: >=3.11
